{
    "pb-IF5SUUxbCQ==": 20, 
    "pb-IF4zUlUOCw==": 30, 
    "pb-IF4KUXYSPA==": 10, 
    "pb-IF4xUxMINA==": 100, 
    "pb-IF4PURUBXA==": 10, 
    "pb-IF4tU1AMJA==": 64, 
    "pb-IF4tUHoMBA==": 10, 
    "pb-IF4OUVQqLw==": 10, 
    "pb-IF4iUUtaBA==": 30, 
    "pb-IF41UXkACQ==": 40, 
    "pb-IF4oUFcbIw==": 60, 
    "pb-IF4IUVAgKA==": 40, 
    "pb-IF4NU3IvEw==": 10, 
    "pb-IF4gUhgYAQ==": 40, 
    "pb-IF4wUW8DXQ==": 10, 
    "pb-IF4rUUQEVQ==": 20, 
    "pb-IF4cUhMyUQ==": 10, 
    "pb-IF4qUU9fAw==": 10, 
    "pb-IF5UUBBTNg==": 260, 
    "pb-IF4DURAjDA==": 10, 
    "pb-IF4zUUpZPQ==": 20, 
    "pb-IF4OUUZTKA==": 10, 
    "pb-IF4zUVQpPA==": 10, 
    "pb-IF4sUFkCEA==": 10, 
    "pb-IF4AUnU9PQ==": 10, 
    "pb-IF5SUW0THQ==": 10, 
    "pb-IF4oUGpbPA==": 100, 
    "pb-IF4tUXlSXA==": 20, 
    "pb-IF4HUVARPw==": 20, 
    "pb-IF4SUVQfBg==": 20, 
    "pb-IF4vUU4MDA==": 10, 
    "pb-IF4hURc7Mg==": 10, 
    "pb-IF4LUXkTVQ==": 10, 
    "pb-IF4mVG8NEQ==": 20, 
    "pb-IF5QUWkOFQ==": 10, 
    "pb-IF43U1URIg==": 20, 
    "pb-IF4BVRcdLA==": 10, 
    "pb-IF4MUkkAEg==": 10, 
    "pb-IF4QVEIOKw==": 10, 
    "pb-IF4FUEoCBA==": 49190, 
    "pb-IF48UVVZCw==": 10, 
    "pb-IF4tUUMxJw==": 50, 
    "pb-IF4sUXYkIQ==": 10, 
    "pb-IF4BUU5aUw==": 10, 
    "pb-IF4sU24yUw==": 10000, 
    "pb-IF4lUU4ZAQ==": 10, 
    "pb-IF4cUVRbLg==": 10, 
    "pb-IF4AUmkxJg==": 40, 
    "pb-IF43UVAOEw==": 10, 
    "pb-IF4VUVASCQ==": 10, 
    "pb-IF43URkvEg==": 30, 
    "pb-IF5RUU0fEQ==": 10, 
    "pb-IF40UUcuUg==": 70, 
    "pb-IF4eUUEqKA==": 40, 
    "pb-IF4UUhQeAw==": 20, 
    "pb-IF4XUVJZCw==": 20, 
    "pb-IF5dUWgkJw==": 10, 
    "pb-JiNJARFZVkpBWVtGEUFRVFRFGURYQllC": 10, 
    "pb-IF4nUUQ9Ig==": 10, 
    "pb-IF4-UGtaKw==": 10, 
    "pb-IF4JUVBTFQ==": 64, 
    "pb-IF4BUUpTLQ==": 10, 
    "pb-IF5dUVYPFw==": 10, 
    "pb-IF4sUVQhUQ==": 10, 
    "pb-IF4iVFNfCQ==": 20, 
    "pb-IF5XUU8REw==": 10, 
    "pb-IF4UUVQoLA==": 10, 
    "pb-IF4MVGEaLA==": 800, 
    "pb-IF43UWpeHQ==": 0, 
    "pb-IF4SVVcJBA==": 10, 
    "pb-IF4OUEgeKQ==": 30, 
    "pb-IF4PUWQPLQ==": 80, 
    "pb-IF5cUXBSNg==": 140, 
    "pb-IF4iU3QPAQ==": 18630, 
    "pb-IF4eUVEnMQ==": 153, 
    "pb-IF4hUUpbIQ==": 10, 
    "pb-IF5XUXNeEg==": 30, 
    "pb-IF4HUWQhKA==": 10, 
    "pb-IF4uVUgOFA==": 10, 
    "pb-IF4zUUsYDg==": 20, 
    "pb-IF5UU3YOXQ==": 10, 
    "pb-IF5dUXIZMg==": 10, 
    "pb-IF4BUUIcCw==": 10, 
    "pb-IF4MUWECVg==": 10, 
    "pb-IF5SA3ge": 20, 
    "pb-IF4SU1VTUQ==": 80, 
    "pb-IF5RUVEIAw==": 9060, 
    "pb-IF4VUGZaHQ==": 20, 
    "pb-IF4cUkMxUg==": 10, 
    "pb-IF5UUWUZMQ==": 250, 
    "pb-IF4DUW5bFg==": 10, 
    "pb-IF4GUFciLQ==": 164, 
    "pb-IF4yUXg-Nw==": 10, 
    "pb-IF42UXEIAQ==": 10, 
    "pb-IF5WUmUoNA==": 10, 
    "pb-IF4UUFEMMg==": 100, 
    "pb-IF4rU1ZfJA==": 30, 
    "pb-IF5RVEsyNQ==": 30, 
    "pb-IF4TUXMaLQ==": 10, 
    "pb-IF4wVUYhUw==": 20, 
    "pb-IF4xURIxVA==": 799, 
    "pb-IF4VUU8YMQ==": 10, 
    "pb-IF4SUWYlDw==": 10, 
    "pb-IF4TUUg-UA==": 10, 
    "pb-IF4yUUJeJA==": 40, 
    "pb-IF4hU1JeIw==": 50, 
    "pb-IF4AURAkCA==": 30, 
    "pb-IF4dVEtZLw==": 50, 
    "pb-IF41UxQmVg==": 10, 
    "pb-IF48UEsHFQ==": 10, 
    "pb-IF4jUVEDLw==": 50, 
    "pb-IF43UUsxXA==": 50, 
    "pb-IF5RUEYlBg==": 90, 
    "pb-IF4AUkIHBA==": 10, 
    "pb-IF40Hnob": 20, 
    "pb-IF4VUhU9NA==": 99999999953239, 
    "pb-IF42UxdZJw==": 40, 
    "pb-JiNJARBZXUNBVVxBFENYU1dCFENXRlBA": 20, 
    "pb-IF4BUXU5Cg==": 10, 
    "pb-IF4TUXVTKg==": 40, 
    "pb-IF5RUXISCA==": 10, 
    "pb-IF5cUXkGBg==": 20, 
    "pb-IF4PVUQ7KA==": 20, 
    "pb-IF4MUVQYJw==": 40, 
    "pb-IF4eUUEHPQ==": 40, 
    "pb-IF4wUnRcMw==": 10, 
    "pb-IF4pURg_Mw==": 9999, 
    "pb-IF4iUXIqMw==": 1000, 
    "pb-IF4CUU5dJg==": 10, 
    "pb-IF4lUmlaLQ==": 700, 
    "pb-IF4AUW9fAQ==": 20, 
    "pb-IF4KVREZKQ==": 20, 
    "pb-IF42UU4MUA==": 400, 
    "pb-IF4IUUFbBg==": 10, 
    "pb-IF40UVMzLg==": 20, 
    "pb-IF4RUWQiJg==": 40, 
    "pb-IF4WUXQfEQ==": 30, 
    "pb-IF4eUVUlAg==": 10, 
    "pb-IF4rUUwdUw==": 10, 
    "pb-IF4FUHkINg==": 40, 
    "pb-IF4yU2o9HA==": 30, 
    "pb-IF4RUWkGNw==": 10, 
    "pb-IF4nUVQDJA==": 80, 
    "pb-IF4gVXcCHA==": 2100, 
    "pb-IF4oUGcFLg==": 10, 
    "pb-IF4GUnU7Dw==": 70, 
    "pb-IF4GUGQRLA==": 10, 
    "pb-IF4GUUwEDA==": 20, 
    "pb-IF4xUVIjDA==": 10, 
    "pb-IF4GUBgnJA==": 50, 
    "pb-IF5VUUhcVQ==": 10, 
    "pb-IF4zUVMcBw==": 20, 
    "pb-IF4CUWkDJA==": 50, 
    "pb-IF5UUXcxVg==": 60, 
    "pb-IF4nUUEoIA==": 11320, 
    "pb-IF4WUUdYIQ==": 10, 
    "pb-IF5SUUpfAw==": 10, 
    "pb-IF4iUUgtBg==": 30, 
    "pb-IF4tUXA8FQ==": 0, 
    "pb-IF4-UWcAFQ==": 30, 
    "pb-IF4OUVMZAw==": 10, 
    "pb-IF5WUU4qFA==": 4740, 
    "pb-IF5UUVEaUA==": 10, 
    "pb-IF4MUU8gUw==": 100
}